README.rst
setup.py
v5rpc/IStrategy.py
v5rpc/V5RPC.py
v5rpc/__init__.py
v5rpc/types.py
v5rpc.egg-info/PKG-INFO
v5rpc.egg-info/SOURCES.txt
v5rpc.egg-info/dependency_links.txt
v5rpc.egg-info/requires.txt
v5rpc.egg-info/top_level.txt
v5rpc/proto/API_pb2.py
v5rpc/proto/DataStructures_pb2.py
v5rpc/proto/Events_pb2.py
v5rpc/proto/__init__.py